cc_net/__init__.py
cc_net/__main__.py
cc_net/dedup.py
cc_net/execution.py
cc_net/flat_hash_set.py
cc_net/get_wiki_cirrus.py
cc_net/jsonql.py
cc_net/mine.py
cc_net/minify.py
cc_net/perplexity.py
cc_net/process_wet_file.py
cc_net/regroup.py
cc_net/split_by_lang.py
cc_net/text_normalizer.py
cc_net/tokenizer.py
cc_net/data/cutoff.csv
cc_net/data/test_stats.json
cc_net-0.0.0.dist-info/LICENSE
cc_net-0.0.0.dist-info/METADATA
cc_net-0.0.0.dist-info/WHEEL
cc_net-0.0.0.dist-info/top_level.txt
cc_net-0.0.0.dist-info/RECORD
